setup.py
ckanext/__init__.py
ckanext/storage/__init__.py
ckanext/storage/controller.py
ckanext_storage.egg-info/PKG-INFO
ckanext_storage.egg-info/SOURCES.txt
ckanext_storage.egg-info/dependency_links.txt
ckanext_storage.egg-info/entry_points.txt
ckanext_storage.egg-info/namespace_packages.txt
ckanext_storage.egg-info/not-zip-safe
ckanext_storage.egg-info/requires.txt
ckanext_storage.egg-info/top_level.txt