Metadata-Version: 1.0
Name: ckanext-storage
Version: 0.6
Summary: CKAN API Extension for OFS Storage
Home-page: http://okfn.org/
Author: Open Knowledge Foundation
Author-email: okfn-dev@lists.okfn.org
License: AGPL
Platform: UNKNOWN
